led_driver_mocks/__init__.py
led_driver_mocks/driver_mocks/__init__.py
led_driver_mocks/driver_mocks/apa102_mock.py
led_driver_mocks/server/__init__.py
led_driver_mocks/server/led_simulator.py
led_driver_mocks/server/runner.py
led_driver_mocks/server/server.py
led_driver_mocks/server/web_socket.py
vomste_led_driver_mocks-0.0.2.dist-info/METADATA
vomste_led_driver_mocks-0.0.2.dist-info/WHEEL
vomste_led_driver_mocks-0.0.2.dist-info/top_level.txt
vomste_led_driver_mocks-0.0.2.dist-info/RECORD
