Metadata-Version: 2.4
Name: vomste-led-driver-mocks
Version: 0.0.2
Summary: A collection of led strip driver_mocks mocks, which are sending the input values to a server for further processing
Author: Vomste
Author-email: luggi.edi@gmail.com
Classifier: Programming Language :: Python :: 3
Classifier: License :: OSI Approved :: MIT License
Classifier: Operating System :: OS Independent
Requires-Python: >=3.6
Requires-Dist: websockets
Dynamic: author
Dynamic: author-email
Dynamic: classifier
Dynamic: description
Dynamic: description-content-type
Dynamic: requires-dist
Dynamic: requires-python
Dynamic: summary
